{"devicePlatform":"","logFolder":"F:\\234project-backend\\234project\\Reports\\TestH\\20180510_120311","runData":{"hostName":"Administrator - 10.80.109.39","os":"Windows 10 64bit","katalonVersion":"5.4.1.1","browser":"Chrome 62.0.3202.94","hostAddress":"10.80.109.39","sessionId":"d33dc29f6ab891451316776474070291","seleniumVersion":"3.7.1","proxyInformation":"ProxyInformation{proxyOption\u003dNO_PROXY, proxyServerType\u003dHTTP, password\u003d, proxyServerAddress\u003d, proxyServerPort\u003d0}","platform":"Windows 10"},"type":"TEST_SUITE","name":"TestH","id":"Test Suites/TestH","source":"","message":"Test Cases/TestH FAILED because (of) Unable to click on object \u0027Object Repository/AddToCarts/a_Carts            5\u0027 (Root cause: com.kms.katalon.core.webui.exception.WebElementNotFoundException: Web element with id: \u0027Object Repository/AddToCarts/a_Carts            5\u0027 located by \u0027By.xpath: //a[@href \u003d \u0027/cart\u0027 and (text() \u003d \u0027Carts\n            5\n          \u0027 or . \u003d \u0027Carts\n            5\n          \u0027)]\u0027 not found)","description":"","startTime":1525928593408,"endTime":1525928648288,"childRecords":[{"isOptional":false,"type":"TEST_CASE","name":"Test Cases/TestH","id":"Test Cases/TestH","source":"F:\\\\234project-backend\\\\234project\\\\Test Cases\\\\TestH.tc","message":"Test Cases/TestH FAILED because (of) Unable to click on object \u0027Object Repository/AddToCarts/a_Carts            5\u0027 (Root cause: com.kms.katalon.core.webui.exception.WebElementNotFoundException: Web element with id: \u0027Object Repository/AddToCarts/a_Carts            5\u0027 located by \u0027By.xpath: //a[@href \u003d \u0027/cart\u0027 and (text() \u003d \u0027Carts\n            5\n          \u0027 or . \u003d \u0027Carts\n            5\n          \u0027)]\u0027 not found)","description":"When the user enters the Products page, and clicked at the add to cart button, the button will be changed to already added, and the number of selected products is shown next to the Carts menu","startTime":1525928594185,"endTime":1525928646667,"childRecords":[{"testStatus":{"stackTrace":"","statusValue":"INFO"},"type":"MESSAGE","name":"","message":"Evaluating variables for test case","startTime":1525928594268,"endTime":0,"childRecords":[],"interuppted":false},{"testStatus":{"stackTrace":"","statusValue":"INFO"},"type":"MESSAGE","name":"","message":"Variable \u0027username\u0027 is set to admin","startTime":1525928594277,"endTime":0,"childRecords":[],"interuppted":false},{"testStatus":{"stackTrace":"","statusValue":"INFO"},"type":"MESSAGE","name":"","message":"Variable \u0027password\u0027 is set to admin","startTime":1525928594281,"endTime":0,"childRecords":[],"interuppted":false},{"testStatus":{"stackTrace":"","statusValue":"INFO"},"type":"MESSAGE","name":"","message":"Variable \u0027product1\u0027 is set to Garden","startTime":1525928594281,"endTime":0,"childRecords":[],"interuppted":false},{"testStatus":{"stackTrace":"","statusValue":"INFO"},"type":"MESSAGE","name":"","message":"Variable \u0027product2\u0027 is set to Banana","startTime":1525928594281,"endTime":0,"childRecords":[],"interuppted":false},{"testStatus":{"stackTrace":"","statusValue":"INFO"},"type":"MESSAGE","name":"","message":"Variable \u0027product3\u0027 is set to Orange","startTime":1525928594289,"endTime":0,"childRecords":[],"interuppted":false},{"testStatus":{"stackTrace":"","statusValue":"INFO"},"type":"MESSAGE","name":"","message":"Variable \u0027product4\u0027 is set to Papaya","startTime":1525928594293,"endTime":0,"childRecords":[],"interuppted":false},{"testStatus":{"stackTrace":"","statusValue":"INFO"},"type":"MESSAGE","name":"","message":"Variable \u0027product5\u0027 is set to Rambutan","startTime":1525928594297,"endTime":0,"childRecords":[],"interuppted":false},{"index":1,"isIgnoredIfFailed":false,"type":"TEST_STEP","name":"openBrowser","message":"Browser is opened with url: \u0027\u0027","description":"","startTime":1525928594914,"endTime":1525928602191,"childRecords":[{"testStatus":{"stackTrace":"","statusValue":"PASSED"},"type":"MESSAGE","name":"","message":"Browser is opened with url: \u0027\u0027","startTime":1525928602187,"endTime":0,"childRecords":[],"interuppted":false}],"interuppted":false},{"index":2,"isIgnoredIfFailed":false,"type":"TEST_STEP","name":"navigateToUrl","message":"Navigate to \u0027http://54.245.190.238:9998/\u0027 successfully","description":"","startTime":1525928602191,"endTime":1525928610701,"childRecords":[{"testStatus":{"stackTrace":"","statusValue":"PASSED"},"type":"MESSAGE","name":"","message":"Navigate to \u0027http://54.245.190.238:9998/\u0027 successfully","startTime":1525928610700,"endTime":0,"childRecords":[],"interuppted":false}],"interuppted":false},{"index":3,"isIgnoredIfFailed":false,"type":"TEST_STEP","name":"setText","message":"Text \u0027admin\u0027 is set on object \u0027Object Repository/AddToCarts/input_username\u0027","description":"","startTime":1525928610703,"endTime":1525928611099,"childRecords":[{"testStatus":{"stackTrace":"","statusValue":"PASSED"},"type":"MESSAGE","name":"","message":"Text \u0027admin\u0027 is set on object \u0027Object Repository/AddToCarts/input_username\u0027","startTime":1525928611097,"endTime":0,"childRecords":[],"interuppted":false}],"interuppted":false},{"index":4,"isIgnoredIfFailed":false,"type":"TEST_STEP","name":"setText","message":"Text \u0027admin\u0027 is set on object \u0027Object Repository/AddToCarts/input_password\u0027","description":"","startTime":1525928611099,"endTime":1525928611422,"childRecords":[{"testStatus":{"stackTrace":"","statusValue":"PASSED"},"type":"MESSAGE","name":"","message":"Text \u0027admin\u0027 is set on object \u0027Object Repository/AddToCarts/input_password\u0027","startTime":1525928611421,"endTime":0,"childRecords":[],"interuppted":false}],"interuppted":false},{"index":5,"isIgnoredIfFailed":false,"type":"TEST_STEP","name":"click","message":"Object: \u0027Object Repository/AddToCarts/button_Login\u0027 is clicked on","description":"","startTime":1525928611423,"endTime":1525928611650,"childRecords":[{"testStatus":{"stackTrace":"","statusValue":"PASSED"},"type":"MESSAGE","name":"","message":"Object: \u0027Object Repository/AddToCarts/button_Login\u0027 is clicked on","startTime":1525928611649,"endTime":0,"childRecords":[],"interuppted":false}],"interuppted":false},{"index":6,"isIgnoredIfFailed":false,"type":"TEST_STEP","name":"click","message":"Object: \u0027Object Repository/AddToCarts/button_add to cart\u0027 is clicked on","description":"","startTime":1525928611651,"endTime":1525928612918,"childRecords":[{"testStatus":{"stackTrace":"","statusValue":"PASSED"},"type":"MESSAGE","name":"","message":"Object: \u0027Object Repository/AddToCarts/button_add to cart\u0027 is clicked on","startTime":1525928612917,"endTime":0,"childRecords":[],"interuppted":false}],"interuppted":false},{"index":7,"isIgnoredIfFailed":false,"type":"TEST_STEP","name":"verifyElementText","message":"Actual text and expected text of test object \u0027Object Repository/AddToCarts/div_already added\u0027 are matched.","description":"","startTime":1525928612919,"endTime":1525928613648,"childRecords":[{"testStatus":{"stackTrace":"","statusValue":"PASSED"},"type":"MESSAGE","name":"","message":"Actual text and expected text of test object \u0027Object Repository/AddToCarts/div_already added\u0027 are matched.","startTime":1525928613645,"endTime":0,"childRecords":[],"interuppted":false}],"interuppted":false},{"index":8,"isIgnoredIfFailed":false,"type":"TEST_STEP","name":"click","message":"Object: \u0027Object Repository/AddToCarts/button_add to cart\u0027 is clicked on","description":"","startTime":1525928613648,"endTime":1525928613856,"childRecords":[{"testStatus":{"stackTrace":"","statusValue":"PASSED"},"type":"MESSAGE","name":"","message":"Object: \u0027Object Repository/AddToCarts/button_add to cart\u0027 is clicked on","startTime":1525928613856,"endTime":0,"childRecords":[],"interuppted":false}],"interuppted":false},{"index":9,"isIgnoredIfFailed":false,"type":"TEST_STEP","name":"verifyElementText","message":"Actual text and expected text of test object \u0027Object Repository/AddToCarts/div_already added\u0027 are matched.","description":"","startTime":1525928613856,"endTime":1525928613914,"childRecords":[{"testStatus":{"stackTrace":"","statusValue":"PASSED"},"type":"MESSAGE","name":"","message":"Actual text and expected text of test object \u0027Object Repository/AddToCarts/div_already added\u0027 are matched.","startTime":1525928613914,"endTime":0,"childRecords":[],"interuppted":false}],"interuppted":false},{"index":10,"isIgnoredIfFailed":false,"type":"TEST_STEP","name":"click","message":"Object: \u0027Object Repository/AddToCarts/button_add to cart\u0027 is clicked on","description":"","startTime":1525928613914,"endTime":1525928614042,"childRecords":[{"testStatus":{"stackTrace":"","statusValue":"PASSED"},"type":"MESSAGE","name":"","message":"Object: \u0027Object Repository/AddToCarts/button_add to cart\u0027 is clicked on","startTime":1525928614042,"endTime":0,"childRecords":[],"interuppted":false}],"interuppted":false},{"index":11,"isIgnoredIfFailed":false,"type":"TEST_STEP","name":"verifyElementText","message":"Actual text and expected text of test object \u0027Object Repository/AddToCarts/div_already added\u0027 are matched.","description":"","startTime":1525928614042,"endTime":1525928614098,"childRecords":[{"testStatus":{"stackTrace":"","statusValue":"PASSED"},"type":"MESSAGE","name":"","message":"Actual text and expected text of test object \u0027Object Repository/AddToCarts/div_already added\u0027 are matched.","startTime":1525928614098,"endTime":0,"childRecords":[],"interuppted":false}],"interuppted":false},{"index":12,"isIgnoredIfFailed":false,"type":"TEST_STEP","name":"click","message":"Object: \u0027Object Repository/AddToCarts/button_add to cart\u0027 is clicked on","description":"","startTime":1525928614102,"endTime":1525928614220,"childRecords":[{"testStatus":{"stackTrace":"","statusValue":"PASSED"},"type":"MESSAGE","name":"","message":"Object: \u0027Object Repository/AddToCarts/button_add to cart\u0027 is clicked on","startTime":1525928614216,"endTime":0,"childRecords":[],"interuppted":false}],"interuppted":false},{"index":13,"isIgnoredIfFailed":false,"type":"TEST_STEP","name":"verifyElementText","message":"Actual text and expected text of test object \u0027Object Repository/AddToCarts/div_already added\u0027 are matched.","description":"","startTime":1525928614220,"endTime":1525928614260,"childRecords":[{"testStatus":{"stackTrace":"","statusValue":"PASSED"},"type":"MESSAGE","name":"","message":"Actual text and expected text of test object \u0027Object Repository/AddToCarts/div_already added\u0027 are matched.","startTime":1525928614260,"endTime":0,"childRecords":[],"interuppted":false}],"interuppted":false},{"index":14,"isIgnoredIfFailed":false,"type":"TEST_STEP","name":"click","message":"Object: \u0027Object Repository/AddToCarts/button_add to cart\u0027 is clicked on","description":"","startTime":1525928614260,"endTime":1525928614392,"childRecords":[{"testStatus":{"stackTrace":"","statusValue":"PASSED"},"type":"MESSAGE","name":"","message":"Object: \u0027Object Repository/AddToCarts/button_add to cart\u0027 is clicked on","startTime":1525928614392,"endTime":0,"childRecords":[],"interuppted":false}],"interuppted":false},{"index":15,"isIgnoredIfFailed":false,"type":"TEST_STEP","name":"verifyElementText","message":"Actual text and expected text of test object \u0027Object Repository/AddToCarts/div_already added\u0027 are matched.","description":"","startTime":1525928614396,"endTime":1525928614443,"childRecords":[{"testStatus":{"stackTrace":"","statusValue":"PASSED"},"type":"MESSAGE","name":"","message":"Actual text and expected text of test object \u0027Object Repository/AddToCarts/div_already added\u0027 are matched.","startTime":1525928614440,"endTime":0,"childRecords":[],"interuppted":false}],"interuppted":false},{"attachment":"1525928646061.png","index":16,"isIgnoredIfFailed":false,"type":"TEST_STEP","name":"click","message":"Unable to click on object \u0027Object Repository/AddToCarts/a_Carts            5\u0027 (Root cause: com.kms.katalon.core.webui.exception.WebElementNotFoundException: Web element with id: \u0027Object Repository/AddToCarts/a_Carts            5\u0027 located by \u0027By.xpath: //a[@href \u003d \u0027/cart\u0027 and (text() \u003d \u0027Carts\n            5\n          \u0027 or . \u003d \u0027Carts\n            5\n          \u0027)]\u0027 not found)","description":"","startTime":1525928614443,"endTime":1525928646666,"childRecords":[{"testStatus":{"stackTrace":"","statusValue":"FAILED"},"attachment":"1525928646061.png","type":"MESSAGE","name":"","message":"Unable to click on object \u0027Object Repository/AddToCarts/a_Carts            5\u0027 (Root cause: com.kms.katalon.core.webui.exception.WebElementNotFoundException: Web element with id: \u0027Object Repository/AddToCarts/a_Carts            5\u0027 located by \u0027By.xpath: //a[@href \u003d \u0027/cart\u0027 and (text() \u003d \u0027Carts\n            5\n          \u0027 or . \u003d \u0027Carts\n            5\n          \u0027)]\u0027 not found)","startTime":1525928646665,"endTime":0,"childRecords":[],"interuppted":false}],"interuppted":false},{"testStatus":{"stackTrace":"","statusValue":"FAILED"},"type":"MESSAGE","name":"","message":"Test Cases/TestH FAILED because (of) Unable to click on object \u0027Object Repository/AddToCarts/a_Carts            5\u0027 (Root cause: com.kms.katalon.core.webui.exception.WebElementNotFoundException: Web element with id: \u0027Object Repository/AddToCarts/a_Carts            5\u0027 located by \u0027By.xpath: //a[@href \u003d \u0027/cart\u0027 and (text() \u003d \u0027Carts\n            5\n          \u0027 or . \u003d \u0027Carts\n            5\n          \u0027)]\u0027 not found)","startTime":1525928646666,"endTime":0,"childRecords":[],"interuppted":false}],"interuppted":false}],"interuppted":false}